{
  "sched_debug.time": [
    1480997600.2291553
  ],
  "sched_debug.ktime": [
    8734770.56961
  ],
  "sched_debug.sched_clk": [
    8734870.093048
  ],
  "sched_debug.cpu_clk": [
    8734870.093116
  ],
  "sched_debug.jiffies": [
    4303402067
  ],
  "sched_debug.sched_clock_stable()": [
    1
  ],
  "sched_debug.sysctl_sched.sysctl_sched_latency": [
    9.999999
  ],
  "sched_debug.sysctl_sched.sysctl_sched_min_granularity": [
    2.25
  ],
  "sched_debug.sysctl_sched.sysctl_sched_wakeup_granularity": [
    1.999998
  ],
  "sched_debug.sysctl_sched.sysctl_sched_features": [
    44859
  ],
  "sched_debug.sysctl_sched.sysctl_sched_tunable_scaling": [
    1
  ],
  "sched_debug.cpu.nr_switches.0": [
    5264097
  ],
  "sched_debug.cpu.nr_load_updates.0": [
    3078944
  ],
  "sched_debug.cpu.nr_uninterruptible.0": [
    -1346
  ],
  "sched_debug.cpu.next_balance.0": [
    4303.402075
  ],
  "sched_debug.cpu.clock.0": [
    8734870.527698
  ],
  "sched_debug.cpu.clock_task.0": [
    8734870.527698
  ],
  "sched_debug.cpu.cpu_load[0].0": [
    51
  ],
  "sched_debug.cpu.cpu_load[1].0": [
    52
  ],
  "sched_debug.cpu.cpu_load[2].0": [
    54
  ],
  "sched_debug.cpu.cpu_load[3].0": [
    54
  ],
  "sched_debug.cpu.cpu_load[4].0": [
    66
  ],
  "sched_debug.cpu.yld_count.0": [
    3229
  ],
  "sched_debug.cpu.sched_count.0": [
    5657768
  ],
  "sched_debug.cpu.sched_goidle.0": [
    2523513
  ],
  "sched_debug.cpu.avg_idle.0": [
    353984
  ],
  "sched_debug.cpu.max_idle_balance_cost.0": [
    500000
  ],
  "sched_debug.cpu.ttwu_count.0": [
    3184497
  ],
  "sched_debug.cpu.ttwu_local.0": [
    1248369
  ],
  "sched_debug.cfs_rq:/.exec_clock.0": [
    540207.844356
  ],
  "sched_debug.cfs_rq:/.MIN_vruntime.0": [
    1.0e-06
  ],
  "sched_debug.cfs_rq:/.min_vruntime.0": [
    268937.033052
  ],
  "sched_debug.cfs_rq:/.max_vruntime.0": [
    1.0e-06
  ],
  "sched_debug.cfs_rq:/.nr_spread_over.0": [
    2452
  ],
  "sched_debug.cfs_rq:/.load_avg.0": [
    472
  ],
  "sched_debug.cfs_rq:/.runnable_load_avg.0": [
    51
  ],
  "sched_debug.cfs_rq:/.util_avg.0": [
    395
  ],
  "sched_debug.cfs_rq:/.tg_load_avg_contrib.0": [
    472
  ],
  "sched_debug.cfs_rq:/.tg_load_avg.0": [
    2184
  ],
  "sched_debug.rt_rq:/bg_non_interactive.rt_runtime.0": [
    700.0
  ],
  "sched_debug.rt_rq:/.rt_runtime.0": [
    800.0
  ],
  "sched_debug.cpu.nr_running.1": [
    1
  ],
  "sched_debug.cpu.load.1": [
    1024
  ],
  "sched_debug.cpu.nr_switches.1": [
    5257468
  ],
  "sched_debug.cpu.nr_load_updates.1": [
    2866789
  ],
  "sched_debug.cpu.nr_uninterruptible.1": [
    -874
  ],
  "sched_debug.cpu.next_balance.1": [
    4303.402071
  ],
  "sched_debug.cpu.clock.1": [
    8734871.234442
  ],
  "sched_debug.cpu.clock_task.1": [
    8734871.234442
  ],
  "sched_debug.cpu.cpu_load[0].1": [
    41
  ],
  "sched_debug.cpu.cpu_load[1].1": [
    77
  ],
  "sched_debug.cpu.cpu_load[2].1": [
    125
  ],
  "sched_debug.cpu.cpu_load[3].1": [
    124
  ],
  "sched_debug.cpu.cpu_load[4].1": [
    116
  ],
  "sched_debug.cpu.yld_count.1": [
    3030
  ],
  "sched_debug.cpu.sched_count.1": [
    5555823
  ],
  "sched_debug.cpu.sched_goidle.1": [
    2565594
  ],
  "sched_debug.cpu.avg_idle.1": [
    296990
  ],
  "sched_debug.cpu.max_idle_balance_cost.1": [
    500000
  ],
  "sched_debug.cpu.ttwu_count.1": [
    2430879
  ],
  "sched_debug.cpu.ttwu_local.1": [
    987488
  ],
  "sched_debug.cfs_rq:/bg_non_interactive.exec_clock.1": [
    0.201373
  ],
  "sched_debug.cfs_rq:/bg_non_interactive.MIN_vruntime.1": [
    1.0e-06
  ],
  "sched_debug.cfs_rq:/bg_non_interactive.min_vruntime.1": [
    -1.048576
  ],
  "sched_debug.cfs_rq:/bg_non_interactive.max_vruntime.1": [
    1.0e-06
  ],
  "sched_debug.cfs_rq:/bg_non_interactive.spread0.1": [
    -268938.081628
  ],
  "sched_debug.cfs_rq:/bg_non_interactive.se->exec_start.1": [
    5882765.21991
  ],
  "sched_debug.cfs_rq:/bg_non_interactive.se->vruntime.1": [
    155246.369629
  ],
  "sched_debug.cfs_rq:/bg_non_interactive.se->sum_exec_runtime.1": [
    0.201373
  ],
  "sched_debug.cfs_rq:/bg_non_interactive.se->statistics.exec_max.1": [
    0.068732
  ],
  "sched_debug.cfs_rq:/bg_non_interactive.se->load.weight.1": [
    2
  ],
  "sched_debug.cfs_rq:/bg_non_interactive.se->avg.load_avg.1": [
    980
  ],
  "sched_debug.cfs_rq:/bg_non_interactive.se->avg.util_avg.1": [
    1006
  ],
  "sched_debug.cfs_rq:/.exec_clock.1": [
    523567.679876
  ],
  "sched_debug.cfs_rq:/.MIN_vruntime.1": [
    289731.066963
  ],
  "sched_debug.cfs_rq:/.min_vruntime.1": [
    289736.002448
  ],
  "sched_debug.cfs_rq:/.max_vruntime.1": [
    289731.066963
  ],
  "sched_debug.cfs_rq:/.spread0.1": [
    20798.969396
  ],
  "sched_debug.cfs_rq:/.nr_spread_over.1": [
    3037
  ],
  "sched_debug.cfs_rq:/.nr_running.1": [
    1
  ],
  "sched_debug.cfs_rq:/.load.1": [
    1024
  ],
  "sched_debug.cfs_rq:/.load_avg.1": [
    541
  ],
  "sched_debug.cfs_rq:/.runnable_load_avg.1": [
    59
  ],
  "sched_debug.cfs_rq:/.util_avg.1": [
    443
  ],
  "sched_debug.cfs_rq:/.tg_load_avg_contrib.1": [
    549
  ],
  "sched_debug.cfs_rq:/.tg_load_avg.1": [
    2184
  ],
  "sched_debug.rt_rq:/bg_non_interactive.rt_runtime.1": [
    700.0
  ],
  "sched_debug.rt_rq:/.rt_time.1": [
    0.004426
  ],
  "sched_debug.rt_rq:/.rt_runtime.1": [
    800.0
  ],
  "sched_debug.cpu.nr_running.2": [
    1
  ],
  "sched_debug.cpu.load.2": [
    1024
  ],
  "sched_debug.cpu.nr_switches.2": [
    3952487
  ],
  "sched_debug.cpu.nr_load_updates.2": [
    2121852
  ],
  "sched_debug.cpu.nr_uninterruptible.2": [
    868
  ],
  "sched_debug.cpu.next_balance.2": [
    4303.402192
  ],
  "sched_debug.cpu.curr->pid.2": [
    28575
  ],
  "sched_debug.cpu.clock.2": [
    8734871.535907
  ],
  "sched_debug.cpu.clock_task.2": [
    8734871.535907
  ],
  "sched_debug.cpu.cpu_load[0].2": [
    54
  ],
  "sched_debug.cpu.cpu_load[1].2": [
    44
  ],
  "sched_debug.cpu.cpu_load[2].2": [
    62
  ],
  "sched_debug.cpu.cpu_load[3].2": [
    85
  ],
  "sched_debug.cpu.cpu_load[4].2": [
    99
  ],
  "sched_debug.cpu.yld_count.2": [
    2868
  ],
  "sched_debug.cpu.sched_count.2": [
    4112661
  ],
  "sched_debug.cpu.sched_goidle.2": [
    1917538
  ],
  "sched_debug.cpu.avg_idle.2": [
    254881
  ],
  "sched_debug.cpu.max_idle_balance_cost.2": [
    500000
  ],
  "sched_debug.cpu.ttwu_count.2": [
    1960515
  ],
  "sched_debug.cpu.ttwu_local.2": [
    753150
  ],
  "sched_debug.cfs_rq:/.exec_clock.2": [
    387419.653728
  ],
  "sched_debug.cfs_rq:/.MIN_vruntime.2": [
    1.0e-06
  ],
  "sched_debug.cfs_rq:/.min_vruntime.2": [
    250989.415555
  ],
  "sched_debug.cfs_rq:/.max_vruntime.2": [
    1.0e-06
  ],
  "sched_debug.cfs_rq:/.spread0.2": [
    -17947.617497
  ],
  "sched_debug.cfs_rq:/.nr_spread_over.2": [
    3361
  ],
  "sched_debug.cfs_rq:/.nr_running.2": [
    1
  ],
  "sched_debug.cfs_rq:/.load.2": [
    1024
  ],
  "sched_debug.cfs_rq:/.load_avg.2": [
    617
  ],
  "sched_debug.cfs_rq:/.runnable_load_avg.2": [
    54
  ],
  "sched_debug.cfs_rq:/.util_avg.2": [
    524
  ],
  "sched_debug.cfs_rq:/.tg_load_avg_contrib.2": [
    620
  ],
  "sched_debug.cfs_rq:/.tg_load_avg.2": [
    2184
  ],
  "sched_debug.rt_rq:/bg_non_interactive.rt_runtime.2": [
    700.0
  ],
  "sched_debug.rt_rq:/.rt_time.2": [
    0.005407
  ],
  "sched_debug.rt_rq:/.rt_runtime.2": [
    800.0
  ],
  "sched_debug.cpu.nr_switches.3": [
    3959780
  ],
  "sched_debug.cpu.nr_load_updates.3": [
    2010908
  ],
  "sched_debug.cpu.nr_uninterruptible.3": [
    1352
  ],
  "sched_debug.cpu.next_balance.3": [
    4303.40207
  ],
  "sched_debug.cpu.clock.3": [
    8734871.526396
  ],
  "sched_debug.cpu.clock_task.3": [
    8734871.526396
  ],
  "sched_debug.cpu.cpu_load[0].3": [
    45
  ],
  "sched_debug.cpu.cpu_load[1].3": [
    46
  ],
  "sched_debug.cpu.cpu_load[2].3": [
    51
  ],
  "sched_debug.cpu.cpu_load[3].3": [
    69
  ],
  "sched_debug.cpu.cpu_load[4].3": [
    102
  ],
  "sched_debug.cpu.yld_count.3": [
    3197
  ],
  "sched_debug.cpu.sched_count.3": [
    4115956
  ],
  "sched_debug.cpu.sched_goidle.3": [
    1934137
  ],
  "sched_debug.cpu.avg_idle.3": [
    782532
  ],
  "sched_debug.cpu.max_idle_balance_cost.3": [
    500000
  ],
  "sched_debug.cpu.ttwu_count.3": [
    1849378
  ],
  "sched_debug.cpu.ttwu_local.3": [
    679381
  ],
  "sched_debug.cfs_rq:/.exec_clock.3": [
    379218.118437
  ],
  "sched_debug.cfs_rq:/.MIN_vruntime.3": [
    1.0e-06
  ],
  "sched_debug.cfs_rq:/.min_vruntime.3": [
    264927.640206
  ],
  "sched_debug.cfs_rq:/.max_vruntime.3": [
    1.0e-06
  ],
  "sched_debug.cfs_rq:/.spread0.3": [
    -4009.392846
  ],
  "sched_debug.cfs_rq:/.nr_spread_over.3": [
    3957
  ],
  "sched_debug.cfs_rq:/.load_avg.3": [
    543
  ],
  "sched_debug.cfs_rq:/.runnable_load_avg.3": [
    45
  ],
  "sched_debug.cfs_rq:/.util_avg.3": [
    361
  ],
  "sched_debug.cfs_rq:/.tg_load_avg_contrib.3": [
    543
  ],
  "sched_debug.cfs_rq:/.tg_load_avg.3": [
    2184
  ],
  "sched_debug.rt_rq:/bg_non_interactive.rt_runtime.3": [
    700.0
  ],
  "sched_debug.rt_rq:/.rt_time.3": [
    0.005909
  ],
  "sched_debug.rt_rq:/.rt_runtime.3": [
    800.0
  ],
  "sched_debug.cpu.nr_running.max": [
    1.0
  ],
  "sched_debug.cpu.nr_running.avg": [
    0.5
  ],
  "sched_debug.cpu.nr_running.stddev": [
    0.5
  ],
  "sched_debug.cpu.load.max": [
    1024.0
  ],
  "sched_debug.cpu.load.avg": [
    512.0
  ],
  "sched_debug.cpu.load.stddev": [
    512.0
  ],
  "sched_debug.cpu.nr_switches.max": [
    5264097.0
  ],
  "sched_debug.cpu.nr_switches.min": [
    3952487.0
  ],
  "sched_debug.cpu.nr_switches.avg": [
    4608458.0
  ],
  "sched_debug.cpu.nr_switches.stddev": [
    652333.8062192546
  ],
  "sched_debug.cpu.nr_load_updates.max": [
    3078944.0
  ],
  "sched_debug.cpu.nr_load_updates.min": [
    2010908.0
  ],
  "sched_debug.cpu.nr_load_updates.avg": [
    2519623.25
  ],
  "sched_debug.cpu.nr_load_updates.stddev": [
    461079.4216463011
  ],
  "sched_debug.cpu.nr_uninterruptible.max": [
    1352.0
  ],
  "sched_debug.cpu.nr_uninterruptible.min": [
    -1346.0
  ],
  "sched_debug.cpu.nr_uninterruptible.stddev": [
    1135.4426449627476
  ],
  "sched_debug.cpu.next_balance.max": [
    4303.402192
  ],
  "sched_debug.cpu.next_balance.min": [
    4303.40207
  ],
  "sched_debug.cpu.next_balance.avg": [
    4303.402102
  ],
  "sched_debug.cpu.next_balance.stddev": [
    5.199519181967845e-05
  ],
  "sched_debug.cpu.curr->pid.max": [
    28575.0
  ],
  "sched_debug.cpu.curr->pid.avg": [
    7143.75
  ],
  "sched_debug.cpu.curr->pid.stddev": [
    12373.337956570167
  ],
  "sched_debug.cpu.clock.max": [
    8734871.535907
  ],
  "sched_debug.cpu.clock.min": [
    8734870.527698
  ],
  "sched_debug.cpu.clock.avg": [
    8734871.20611075
  ],
  "sched_debug.cpu.clock.stddev": [
    0.409998392194262
  ],
  "sched_debug.cpu.clock_task.max": [
    8734871.535907
  ],
  "sched_debug.cpu.clock_task.min": [
    8734870.527698
  ],
  "sched_debug.cpu.clock_task.avg": [
    8734871.20611075
  ],
  "sched_debug.cpu.clock_task.stddev": [
    0.409998392194262
  ],
  "sched_debug.cpu.cpu_load[0].max": [
    54.0
  ],
  "sched_debug.cpu.cpu_load[0].min": [
    41.0
  ],
  "sched_debug.cpu.cpu_load[0].avg": [
    47.75
  ],
  "sched_debug.cpu.cpu_load[0].stddev": [
    5.0682837331783235
  ],
  "sched_debug.cpu.cpu_load[1].max": [
    77.0
  ],
  "sched_debug.cpu.cpu_load[1].min": [
    44.0
  ],
  "sched_debug.cpu.cpu_load[1].avg": [
    54.75
  ],
  "sched_debug.cpu.cpu_load[1].stddev": [
    13.179055353097201
  ],
  "sched_debug.cpu.cpu_load[2].max": [
    125.0
  ],
  "sched_debug.cpu.cpu_load[2].min": [
    51.0
  ],
  "sched_debug.cpu.cpu_load[2].avg": [
    73.0
  ],
  "sched_debug.cpu.cpu_load[2].stddev": [
    30.29026246172192
  ],
  "sched_debug.cpu.cpu_load[3].max": [
    124.0
  ],
  "sched_debug.cpu.cpu_load[3].min": [
    54.0
  ],
  "sched_debug.cpu.cpu_load[3].avg": [
    83.0
  ],
  "sched_debug.cpu.cpu_load[3].stddev": [
    26.086394921491163
  ],
  "sched_debug.cpu.cpu_load[4].max": [
    116.0
  ],
  "sched_debug.cpu.cpu_load[4].min": [
    66.0
  ],
  "sched_debug.cpu.cpu_load[4].avg": [
    95.75
  ],
  "sched_debug.cpu.cpu_load[4].stddev": [
    18.335416548308903
  ],
  "sched_debug.cpu.yld_count.max": [
    3229.0
  ],
  "sched_debug.cpu.yld_count.min": [
    2868.0
  ],
  "sched_debug.cpu.yld_count.avg": [
    3081.0
  ],
  "sched_debug.cpu.yld_count.stddev": [
    144.3346805171924
  ],
  "sched_debug.cpu.sched_count.max": [
    5657768.0
  ],
  "sched_debug.cpu.sched_count.min": [
    4112661.0
  ],
  "sched_debug.cpu.sched_count.avg": [
    4860552.0
  ],
  "sched_debug.cpu.sched_count.stddev": [
    747114.3261231844
  ],
  "sched_debug.cpu.sched_goidle.max": [
    2565594.0
  ],
  "sched_debug.cpu.sched_goidle.min": [
    1917538.0
  ],
  "sched_debug.cpu.sched_goidle.avg": [
    2235195.5
  ],
  "sched_debug.cpu.sched_goidle.stddev": [
    309771.1483244526
  ],
  "sched_debug.cpu.avg_idle.max": [
    782532.0
  ],
  "sched_debug.cpu.avg_idle.min": [
    254881.0
  ],
  "sched_debug.cpu.avg_idle.avg": [
    422096.75
  ],
  "sched_debug.cpu.avg_idle.stddev": [
    211048.40801268202
  ],
  "sched_debug.cpu.max_idle_balance_cost.max": [
    500000.0
  ],
  "sched_debug.cpu.max_idle_balance_cost.min": [
    500000.0
  ],
  "sched_debug.cpu.max_idle_balance_cost.avg": [
    500000.0
  ],
  "sched_debug.cpu.ttwu_count.max": [
    3184497.0
  ],
  "sched_debug.cpu.ttwu_count.min": [
    1849378.0
  ],
  "sched_debug.cpu.ttwu_count.avg": [
    2356317.25
  ],
  "sched_debug.cpu.ttwu_count.stddev": [
    525615.8238601531
  ],
  "sched_debug.cpu.ttwu_local.max": [
    1248369.0
  ],
  "sched_debug.cpu.ttwu_local.min": [
    679381.0
  ],
  "sched_debug.cpu.ttwu_local.avg": [
    917097.0
  ],
  "sched_debug.cpu.ttwu_local.stddev": [
    222532.88876590805
  ],
  "sched_debug.cfs_rq:/.exec_clock.max": [
    540207.844356
  ],
  "sched_debug.cfs_rq:/.exec_clock.min": [
    379218.118437
  ],
  "sched_debug.cfs_rq:/.exec_clock.avg": [
    457603.32409925
  ],
  "sched_debug.cfs_rq:/.exec_clock.stddev": [
    74573.43872549891
  ],
  "sched_debug.cfs_rq:/.MIN_vruntime.max": [
    289731.066963
  ],
  "sched_debug.cfs_rq:/.MIN_vruntime.min": [
    1.0e-06
  ],
  "sched_debug.cfs_rq:/.MIN_vruntime.avg": [
    72432.7667415
  ],
  "sched_debug.cfs_rq:/.MIN_vruntime.stddev": [
    125457.23212733114
  ],
  "sched_debug.cfs_rq:/.min_vruntime.max": [
    289736.002448
  ],
  "sched_debug.cfs_rq:/.min_vruntime.min": [
    250989.415555
  ],
  "sched_debug.cfs_rq:/.min_vruntime.avg": [
    268647.52281525003
  ],
  "sched_debug.cfs_rq:/.min_vruntime.stddev": [
    13878.527191665447
  ],
  "sched_debug.cfs_rq:/.max_vruntime.max": [
    289731.066963
  ],
  "sched_debug.cfs_rq:/.max_vruntime.min": [
    1.0e-06
  ],
  "sched_debug.cfs_rq:/.max_vruntime.avg": [
    72432.7667415
  ],
  "sched_debug.cfs_rq:/.max_vruntime.stddev": [
    125457.23212733114
  ],
  "sched_debug.cfs_rq:/.spread0.max": [
    20798.969396
  ],
  "sched_debug.cfs_rq:/.spread0.min": [
    -17947.617497
  ],
  "sched_debug.cfs_rq:/.spread0.avg": [
    -289.51023674999976
  ],
  "sched_debug.cfs_rq:/.spread0.stddev": [
    13878.52719166545
  ],
  "sched_debug.cfs_rq:/.nr_spread_over.max": [
    3957.0
  ],
  "sched_debug.cfs_rq:/.nr_spread_over.min": [
    2452.0
  ],
  "sched_debug.cfs_rq:/.nr_spread_over.avg": [
    3201.75
  ],
  "sched_debug.cfs_rq:/.nr_spread_over.stddev": [
    544.2955883525054
  ],
  "sched_debug.cfs_rq:/.nr_running.max": [
    1.0
  ],
  "sched_debug.cfs_rq:/.nr_running.avg": [
    0.5
  ],
  "sched_debug.cfs_rq:/.nr_running.stddev": [
    0.5
  ],
  "sched_debug.cfs_rq:/.load.max": [
    1024.0
  ],
  "sched_debug.cfs_rq:/.load.avg": [
    512.0
  ],
  "sched_debug.cfs_rq:/.load.stddev": [
    512.0
  ],
  "sched_debug.cfs_rq:/.load_avg.max": [
    617.0
  ],
  "sched_debug.cfs_rq:/.load_avg.min": [
    472.0
  ],
  "sched_debug.cfs_rq:/.load_avg.avg": [
    543.25
  ],
  "sched_debug.cfs_rq:/.load_avg.stddev": [
    51.28535365969508
  ],
  "sched_debug.cfs_rq:/.runnable_load_avg.max": [
    59.0
  ],
  "sched_debug.cfs_rq:/.runnable_load_avg.min": [
    45.0
  ],
  "sched_debug.cfs_rq:/.runnable_load_avg.avg": [
    52.25
  ],
  "sched_debug.cfs_rq:/.runnable_load_avg.stddev": [
    5.0682837331783235
  ],
  "sched_debug.cfs_rq:/.util_avg.max": [
    524.0
  ],
  "sched_debug.cfs_rq:/.util_avg.min": [
    361.0
  ],
  "sched_debug.cfs_rq:/.util_avg.avg": [
    430.75
  ],
  "sched_debug.cfs_rq:/.util_avg.stddev": [
    61.21427529588176
  ],
  "sched_debug.cfs_rq:/.tg_load_avg_contrib.max": [
    620.0
  ],
  "sched_debug.cfs_rq:/.tg_load_avg_contrib.min": [
    472.0
  ],
  "sched_debug.cfs_rq:/.tg_load_avg_contrib.avg": [
    546.0
  ],
  "sched_debug.cfs_rq:/.tg_load_avg_contrib.stddev": [
    52.36888389110465
  ],
  "sched_debug.cfs_rq:/.tg_load_avg.max": [
    2184.0
  ],
  "sched_debug.cfs_rq:/.tg_load_avg.min": [
    2184.0
  ],
  "sched_debug.cfs_rq:/.tg_load_avg.avg": [
    2184.0
  ],
  "sched_debug.rt_rq:/bg_non_interactive.rt_runtime.max": [
    700.0
  ],
  "sched_debug.rt_rq:/bg_non_interactive.rt_runtime.min": [
    700.0
  ],
  "sched_debug.rt_rq:/bg_non_interactive.rt_runtime.avg": [
    700.0
  ],
  "sched_debug.rt_rq:/.rt_time.max": [
    0.005909
  ],
  "sched_debug.rt_rq:/.rt_time.avg": [
    0.003935500000000001
  ],
  "sched_debug.rt_rq:/.rt_time.stddev": [
    0.002333921860302954
  ],
  "sched_debug.rt_rq:/.rt_runtime.max": [
    800.0
  ],
  "sched_debug.rt_rq:/.rt_runtime.min": [
    800.0
  ],
  "sched_debug.rt_rq:/.rt_runtime.avg": [
    800.0
  ],
  "sched_debug.cfs_rq:/bg_non_interactive.exec_clock.max": [
    0.201373
  ],
  "sched_debug.cfs_rq:/bg_non_interactive.exec_clock.min": [
    0.201373
  ],
  "sched_debug.cfs_rq:/bg_non_interactive.exec_clock.avg": [
    0.201373
  ],
  "sched_debug.cfs_rq:/bg_non_interactive.MIN_vruntime.max": [
    1.0e-06
  ],
  "sched_debug.cfs_rq:/bg_non_interactive.MIN_vruntime.min": [
    1.0e-06
  ],
  "sched_debug.cfs_rq:/bg_non_interactive.MIN_vruntime.avg": [
    1.0e-06
  ],
  "sched_debug.cfs_rq:/bg_non_interactive.min_vruntime.max": [
    -1.048576
  ],
  "sched_debug.cfs_rq:/bg_non_interactive.min_vruntime.min": [
    -1.048576
  ],
  "sched_debug.cfs_rq:/bg_non_interactive.min_vruntime.avg": [
    -1.048576
  ],
  "sched_debug.cfs_rq:/bg_non_interactive.max_vruntime.max": [
    1.0e-06
  ],
  "sched_debug.cfs_rq:/bg_non_interactive.max_vruntime.min": [
    1.0e-06
  ],
  "sched_debug.cfs_rq:/bg_non_interactive.max_vruntime.avg": [
    1.0e-06
  ],
  "sched_debug.cfs_rq:/bg_non_interactive.spread0.max": [
    -268938.081628
  ],
  "sched_debug.cfs_rq:/bg_non_interactive.spread0.min": [
    -268938.081628
  ],
  "sched_debug.cfs_rq:/bg_non_interactive.spread0.avg": [
    -268938.081628
  ],
  "sched_debug.cfs_rq:/bg_non_interactive.se->exec_start.max": [
    5882765.21991
  ],
  "sched_debug.cfs_rq:/bg_non_interactive.se->exec_start.min": [
    5882765.21991
  ],
  "sched_debug.cfs_rq:/bg_non_interactive.se->exec_start.avg": [
    5882765.21991
  ],
  "sched_debug.cfs_rq:/bg_non_interactive.se->vruntime.max": [
    155246.369629
  ],
  "sched_debug.cfs_rq:/bg_non_interactive.se->vruntime.min": [
    155246.369629
  ],
  "sched_debug.cfs_rq:/bg_non_interactive.se->vruntime.avg": [
    155246.369629
  ],
  "sched_debug.cfs_rq:/bg_non_interactive.se->sum_exec_runtime.max": [
    0.201373
  ],
  "sched_debug.cfs_rq:/bg_non_interactive.se->sum_exec_runtime.min": [
    0.201373
  ],
  "sched_debug.cfs_rq:/bg_non_interactive.se->sum_exec_runtime.avg": [
    0.201373
  ],
  "sched_debug.cfs_rq:/bg_non_interactive.se->statistics.exec_max.max": [
    0.068732
  ],
  "sched_debug.cfs_rq:/bg_non_interactive.se->statistics.exec_max.min": [
    0.068732
  ],
  "sched_debug.cfs_rq:/bg_non_interactive.se->statistics.exec_max.avg": [
    0.068732
  ],
  "sched_debug.cfs_rq:/bg_non_interactive.se->load.weight.max": [
    2.0
  ],
  "sched_debug.cfs_rq:/bg_non_interactive.se->load.weight.min": [
    2.0
  ],
  "sched_debug.cfs_rq:/bg_non_interactive.se->load.weight.avg": [
    2.0
  ],
  "sched_debug.cfs_rq:/bg_non_interactive.se->avg.load_avg.max": [
    980.0
  ],
  "sched_debug.cfs_rq:/bg_non_interactive.se->avg.load_avg.min": [
    980.0
  ],
  "sched_debug.cfs_rq:/bg_non_interactive.se->avg.load_avg.avg": [
    980.0
  ],
  "sched_debug.cfs_rq:/bg_non_interactive.se->avg.util_avg.max": [
    1006.0
  ],
  "sched_debug.cfs_rq:/bg_non_interactive.se->avg.util_avg.min": [
    1006.0
  ],
  "sched_debug.cfs_rq:/bg_non_interactive.se->avg.util_avg.avg": [
    1006.0
  ]
}